phylorun/__init__.py
phylorun/engines/__init__.py
phylorun/engines/beast2.py
phylorun/engines/beastX.py
phylorun/engines/engine.py
phylorun/engines/lphy.py
phylorun/engines/revBayes.py
phylorun/jars/convertToLPhy.jar
phylorun/main.py
phylorun/utils/docker_utils.py
phylorun/utils/phylospec_utils.py
phylorun-0.9.0.dist-info/WHEEL
phylorun-0.9.0.dist-info/entry_points.txt
phylorun-0.9.0.dist-info/METADATA
phylorun-0.9.0.dist-info/RECORD
