Metadata-Version: 2.3
Name: phylorun
Version: 0.9.0
Summary: Add your description here
Requires-Dist: click>=8.3.0
Requires-Dist: docker>=7.1.0
Requires-Dist: loguru>=0.7.3
Requires-Dist: pyright>=1.1.406
Requires-Dist: pytest>=8.4.2
Requires-Dist: ruff>=0.14.0
Requires-Python: >=3.10
